shellkit/__init__.py
shellkit/i18n/__init__.py
shellkit/i18n/core.py
shellkit/i18n/lang/__init__.py
shellkit/i18n/lang/en.json
shellkit/i18n/lang/ja.json
shellkit/i18n/lang/ko.json
shellkit/i18n/lang/zh.json
shellkit/inspector/__init__.py
shellkit/inspector/debug/__init__.py
shellkit/inspector/debug/command.py
shellkit/inspector/debug/core.py
shellkit/inspector/debug/layers.py
shellkit/inspector/probe/__init__.py
shellkit/inspector/trace/__init__.py
shellkit/inspector/trace/context.py
shellkit/inspector/trace/core.py
shellkit/inspector/trace/decorator.py
shellkit/inspector/trace/format.py
shellkit/inspector/trace/printer.py
shellkit/inspector/trace/tree.py
shellkit/libc/__init__.py
shellkit/libc/exit/__init__.py
shellkit/libc/exit/hooks.py
shellkit/libc/exit/internal.py
shellkit/libc/printf/__init__.py
shellkit/libc/printf/format.py
shellkit/libc/printf/internal.py
shellkit/libc/printf/parser.py
shellkit/libc/printf/renderer.py
shellkit/libc/printf/specmeta.py
shellkit/libc/printf/types.py
shellkit/libc/printf/utils.py
shellkit/libc/write/__init__.py
shellkit/libc/write/constants.py
shellkit/libc/write/internal.py
shellkit/libc/write/utils.py
shellkit/shell/__init__.py
shellkit/shell/app.py
shellkit/shell/main.py
shellkit/shell/docs/__init__.py
shellkit/shell/docs/manuals/__init__.py
shellkit/shell/docs/manuals/en/alias.md
shellkit/shell/docs/manuals/en/arch.md
shellkit/shell/docs/manuals/en/cd.md
shellkit/shell/docs/manuals/en/clear.md
shellkit/shell/docs/manuals/en/copyright.md
shellkit/shell/docs/manuals/en/date.md
shellkit/shell/docs/manuals/en/echo.md
shellkit/shell/docs/manuals/en/env.md
shellkit/shell/docs/manuals/en/exit.md
shellkit/shell/docs/manuals/en/export.md
shellkit/shell/docs/manuals/en/help.md
shellkit/shell/docs/manuals/en/license.md
shellkit/shell/docs/manuals/en/locale.md
shellkit/shell/docs/manuals/en/machinfo.md
shellkit/shell/docs/manuals/en/printf.md
shellkit-0.1.0.dist-info/METADATA
shellkit-0.1.0.dist-info/WHEEL
shellkit-0.1.0.dist-info/entry_points.txt
shellkit-0.1.0.dist-info/top_level.txt
shellkit-0.1.0.dist-info/RECORD
shellkit-0.1.0.dist-info/licenses/LICENSE
