Metadata-Version: 2.4
Name: ShellKit
Version: 0.1.0
Summary: A teaching-oriented simulation of system call formatting in Python
Author: Pokeya
License-Expression: MIT
Keywords: shell,libc,syscall
Classifier: Programming Language :: Python :: 3
Classifier: Programming Language :: Python :: 3.10
Classifier: Programming Language :: Python :: 3.11
Classifier: Programming Language :: Python :: 3.12
Classifier: Programming Language :: Python :: 3.13
Classifier: Operating System :: OS Independent
Classifier: Topic :: System :: Shells
Requires-Python: >=3.10
License-File: LICENSE
Requires-Dist: tomli; python_version < "3.11"
Provides-Extra: dev
Requires-Dist: black; extra == "dev"
Requires-Dist: isort; extra == "dev"
Requires-Dist: ruff; extra == "dev"
Requires-Dist: mypy; extra == "dev"
Requires-Dist: pytest; extra == "dev"
Requires-Dist: build; extra == "dev"
Requires-Dist: twine; extra == "dev"
Requires-Dist: types-setuptools; extra == "dev"
Dynamic: license-file
